flask_blueprints_loader/__init__.py
flask_blueprints_loader/blueprints_loader.py
flask_blueprints_loader-0.1.1.dist-info/LICENSE
flask_blueprints_loader-0.1.1.dist-info/WHEEL
flask_blueprints_loader-0.1.1.dist-info/METADATA
flask_blueprints_loader-0.1.1.dist-info/RECORD
