Metadata-Version: 2.1
Name: flask-blueprints-loader
Version: 0.1.1
Summary: Automatically discover and register Flask blueprints
Keywords: Flask,blueprint,extension,loader,import,auto-load,auto-import,web framework,Python
Author-email: curskey <ekentiako@proton.me>
Requires-Python: >=3.10
Classifier: Framework :: Flask
Classifier: Environment :: Web Environment
Classifier: Intended Audience :: Developers
Classifier: Development Status :: 3 - Alpha
Classifier: License :: OSI Approved :: MIT License
Classifier: Operating System :: OS Independent
Classifier: Programming Language :: Python :: 3.10
Classifier: Programming Language :: Python :: 3.11
Classifier: Programming Language :: Python :: 3.12
Classifier: Programming Language :: Python :: 3 :: Only
Requires-Dist: flask>=3.0
Requires-Dist: pre-commit>=3.3 ; extra == "develop"
Requires-Dist: pytest>=7.4 ; extra == "develop"
Requires-Dist: pytest-cov>=4.1 ; extra == "develop"
Project-URL: Documentation, https://flask-blueprints-loader.readthedocs.io/en/stable/
Project-URL: Home, https://github.com/curskey/flask-blueprints-loader
Project-URL: Issue, https://github.com/curskey/flask-blueprints-loader/issues/
Project-URL: Source, https://github.com/curskey/flask-blueprints-loader
Provides-Extra: develop
